FuzaxingSiweiZhongwenDierBan/README.md
FuzaxingSiweiZhongwenDierBan/__init__.py
FuzaxingSiweiZhongwenDierBan/__main__.py
FuzaxingSiweiZhongwenDierBan/file.epub
FuzaxingSiweiZhongwenDierBan/index.html
FuzaxingSiweiZhongwenDierBan/css/__init__.py
FuzaxingSiweiZhongwenDierBan/css/annotations.css
FuzaxingSiweiZhongwenDierBan/css/main.css
FuzaxingSiweiZhongwenDierBan/css/normalize.css
FuzaxingSiweiZhongwenDierBan/css/popup.css
FuzaxingSiweiZhongwenDierBan/font/__init__.py
FuzaxingSiweiZhongwenDierBan/font/fontello.eot
FuzaxingSiweiZhongwenDierBan/font/fontello.svg
FuzaxingSiweiZhongwenDierBan/font/fontello.ttf
FuzaxingSiweiZhongwenDierBan/font/fontello.woff
FuzaxingSiweiZhongwenDierBan/img/__init__.py
FuzaxingSiweiZhongwenDierBan/img/annotator-glyph-sprite.png
FuzaxingSiweiZhongwenDierBan/img/annotator-icon-sprite.png
FuzaxingSiweiZhongwenDierBan/img/apple-touch-icon.png
FuzaxingSiweiZhongwenDierBan/img/cancelfullscreen.png
FuzaxingSiweiZhongwenDierBan/img/close.png
FuzaxingSiweiZhongwenDierBan/img/fullscreen.png
FuzaxingSiweiZhongwenDierBan/img/loader.gif
FuzaxingSiweiZhongwenDierBan/img/menu-icon.png
FuzaxingSiweiZhongwenDierBan/img/save.png
FuzaxingSiweiZhongwenDierBan/img/saved.png
FuzaxingSiweiZhongwenDierBan/img/settings-s.png
FuzaxingSiweiZhongwenDierBan/img/settings.png
FuzaxingSiweiZhongwenDierBan/img/star.png
FuzaxingSiweiZhongwenDierBan/js/__init__.py
FuzaxingSiweiZhongwenDierBan/js/epub.js
FuzaxingSiweiZhongwenDierBan/js/epub.min.js
FuzaxingSiweiZhongwenDierBan/js/epub.min.map
FuzaxingSiweiZhongwenDierBan/js/hooks.min.js
FuzaxingSiweiZhongwenDierBan/js/hooks.min.map
FuzaxingSiweiZhongwenDierBan/js/reader.js
FuzaxingSiweiZhongwenDierBan/js/reader.js.map
FuzaxingSiweiZhongwenDierBan/js/reader.min.js
FuzaxingSiweiZhongwenDierBan/js/reader.min.map
FuzaxingSiweiZhongwenDierBan/js/hooks/__init__.py
FuzaxingSiweiZhongwenDierBan/js/hooks/extensions/__init__.py
FuzaxingSiweiZhongwenDierBan/js/hooks/extensions/highlight.js
fuzaxing_siwei_zhongwen_dier_ban-2024.3.3.0.dist-info/METADATA
fuzaxing_siwei_zhongwen_dier_ban-2024.3.3.0.dist-info/WHEEL
fuzaxing_siwei_zhongwen_dier_ban-2024.3.3.0.dist-info/entry_points.txt
fuzaxing_siwei_zhongwen_dier_ban-2024.3.3.0.dist-info/top_level.txt
fuzaxing_siwei_zhongwen_dier_ban-2024.3.3.0.dist-info/RECORD
